Metadata-Version: 2.1
Name: qlogging
Version: 1.2.9
Summary: Beautifully colored, quick and simple Python logging.
Home-page: https://github.com/sinkingtitanic/qlogging
Author: Sinking Titanic
Author-email: ofcourse7878@gmail.com
License: MIT
Platform: UNKNOWN
Classifier: Development Status :: 5 - Production/Stable
Classifier: Environment :: Console
Classifier: Intended Audience :: Developers
Classifier: License :: OSI Approved :: Apache Software License
Classifier: Operating System :: OS Independent
Classifier: Programming Language :: Python :: 3 :: Only
Classifier: Topic :: System :: Logging
Classifier: Topic :: System :: Monitoring
